[
  {
    "id": "net-001",
    "category": ".NET",
    "difficulty": "easy",
    "type": "true-false",
    "question": ".NET is a cross-platform, open-source framework.",
    "options": [
      "False",
      "True"
    ],
    "correctAnswer": 1
  },
  {
    "id": "net-002",
    "category": ".NET",
    "difficulty": "easy",
    "type": "multiple-choice",
    "question": "What does CLR stand for in .NET?",
    "options": [
      "Compilation Language Resolver",
      "Common Language Runtime",
      "Common Library Reference",
      "Core Language Repository"
    ],
    "correctAnswer": 1
  },
  {
    "id": "net-003",
    "category": ".NET",
    "difficulty": "easy",
    "type": "true-false",
    "question": "C# is the primary language for .NET development.",
    "options": [
      "True",
      "False"
    ],
    "correctAnswer": 0
  },
  {
    "id": "net-004",
    "category": ".NET",
    "difficulty": "easy",
    "type": "multiple-choice",
    "question": "Which keyword is used to create a class in C#?",
    "options": [
      "struct",
      "interface",
      "Class",
      "class"
    ],
    "correctAnswer": 3
  },
  {
    "id": "net-005",
    "category": ".NET",
    "difficulty": "easy",
    "type": "true-false",
    "question": "In C#, the string type is a reference type.",
    "options": [
      "False",
      "True"
    ],
    "correctAnswer": 1
  },
  {
    "id": "net-006",
    "category": ".NET",
    "difficulty": "easy",
    "type": "multiple-choice",
    "question": "What is the purpose of the 'using' statement in C#?",
    "options": [
      "Import namespaces",
      "Create disposal scope for resources",
      "Define variable scope",
      "Both A and B"
    ],
    "correctAnswer": 3
  },
  {
    "id": "net-007",
    "category": ".NET",
    "difficulty": "easy",
    "type": "true-false",
    "question": "Abstract classes can be instantiated in C#.",
    "options": [
      "True",
      "False"
    ],
    "correctAnswer": 1
  },
  {
    "id": "net-008",
    "category": ".NET",
    "difficulty": "easy",
    "type": "multiple-choice",
    "question": "Which collection type maintains insertion order and allows duplicates in .NET?",
    "options": [
      "List",
      "Queue",
      "HashSet",
      "Dictionary"
    ],
    "correctAnswer": 0
  },
  {
    "id": "net-009",
    "category": ".NET",
    "difficulty": "easy",
    "type": "true-false",
    "question": "Nullable types in C# are declared using the '?' operator.",
    "options": [
      "False",
      "True"
    ],
    "correctAnswer": 1
  },
  {
    "id": "net-010",
    "category": ".NET",
    "difficulty": "easy",
    "type": "multiple-choice",
    "question": "What does LINQ stand for?",
    "options": [
      "Language Integrated Query",
      "Logic Integrated Query",
      "Language Interface Query",
      "Linear Integrated Query"
    ],
    "correctAnswer": 0
  },
  {
    "id": "net-011",
    "category": ".NET",
    "difficulty": "easy",
    "type": "true-false",
    "question": "The 'async' keyword in C# automatically makes a method asynchronous.",
    "options": [
      "False",
      "True"
    ],
    "correctAnswer": 0
  },
  {
    "id": "net-012",
    "category": ".NET",
    "difficulty": "easy",
    "type": "multiple-choice",
    "question": "Which access modifier restricts access to the same class only?",
    "options": [
      "private",
      "public",
      "internal",
      "protected"
    ],
    "correctAnswer": 0
  },
  {
    "id": "net-013",
    "category": ".NET",
    "difficulty": "easy",
    "type": "true-false",
    "question": "Value types in C# are allocated on the heap.",
    "options": [
      "False",
      "True"
    ],
    "correctAnswer": 0
  },
  {
    "id": "net-014",
    "category": ".NET",
    "difficulty": "easy",
    "type": "multiple-choice",
    "question": "What is the base class for all types in .NET?",
    "options": [
      "Type",
      "System",
      "Base",
      "Object"
    ],
    "correctAnswer": 3
  },
  {
    "id": "net-015",
    "category": ".NET",
    "difficulty": "easy",
    "type": "true-false",
    "question": "Properties in C# must have both get and set accessors.",
    "options": [
      "False",
      "True"
    ],
    "correctAnswer": 0
  },
  {
    "id": "net-016",
    "category": ".NET",
    "difficulty": "medium",
    "type": "multiple-choice",
    "question": "What is the purpose of Dependency Injection in .NET?",
    "options": [
      "All of the above",
      "Reduce coupling between classes",
      "Manage object lifecycles",
      "Improve testability"
    ],
    "correctAnswer": 0
  },
  {
    "id": "net-017",
    "category": ".NET",
    "difficulty": "medium",
    "type": "true-false",
    "question": "Extension methods in C# must be defined in static classes.",
    "options": [
      "True",
      "False"
    ],
    "correctAnswer": 0
  },
  {
    "id": "net-018",
    "category": ".NET",
    "difficulty": "medium",
    "type": "multiple-choice",
    "question": "Which LINQ method returns a single element or throws an exception?",
    "options": [
      "Single",
      "FirstOrDefault",
      "SingleOrDefault",
      "First"
    ],
    "correctAnswer": 0
  },
  {
    "id": "net-019",
    "category": ".NET",
    "difficulty": "medium",
    "type": "true-false",
    "question": "Delegates in C# are type-safe function pointers.",
    "options": [
      "False",
      "True"
    ],
    "correctAnswer": 1
  },
  {
    "id": "net-020",
    "category": ".NET",
    "difficulty": "medium",
    "type": "multiple-choice",
    "question": "What does the 'where' keyword do in a generic constraint?",
    "options": [
      "Add SQL WHERE clause",
      "Restrict type parameters to specific types",
      "Define method parameters",
      "Filter LINQ results"
    ],
    "correctAnswer": 1
  },
  {
    "id": "net-021",
    "category": ".NET",
    "difficulty": "medium",
    "type": "true-false",
    "question": "Interface members in C# are abstract by default.",
    "options": [
      "True",
      "False"
    ],
    "correctAnswer": 0
  },
  {
    "id": "net-022",
    "category": ".NET",
    "difficulty": "medium",
    "type": "multiple-choice",
    "question": "What is Entity Framework used for?",
    "options": [
      "Object-Relational Mapping",
      "Network communication",
      "Database query optimization",
      "UI framework"
    ],
    "correctAnswer": 0
  },
  {
    "id": "net-023",
    "category": ".NET",
    "difficulty": "medium",
    "type": "true-false",
    "question": "The 'sealed' keyword prevents a class from being inherited.",
    "options": [
      "False",
      "True"
    ],
    "correctAnswer": 1
  },
  {
    "id": "net-024",
    "category": ".NET",
    "difficulty": "medium",
    "type": "multiple-choice",
    "question": "What does 'async' and 'await' enable in C#?",
    "options": [
      "Asynchronous programming",
      "Multithreading",
      "Task scheduling",
      "Parallel processing"
    ],
    "correctAnswer": 0
  },
  {
    "id": "net-025",
    "category": ".NET",
    "difficulty": "medium",
    "type": "true-false",
    "question": "Lambda expressions in C# require explicit parameter types.",
    "options": [
      "True",
      "False"
    ],
    "correctAnswer": 1
  },
  {
    "id": "net-026",
    "category": ".NET",
    "difficulty": "medium",
    "type": "multiple-choice",
    "question": "What is the difference between 'ref' and 'out' parameters?",
    "options": [
      "They are identical",
      "out cannot be used in method parameters",
      "ref must be initialized; out must be assigned in method",
      "ref returns a value; out passes by reference"
    ],
    "correctAnswer": 2
  },
  {
    "id": "net-027",
    "category": ".NET",
    "difficulty": "medium",
    "type": "true-false",
    "question": "Struct types in C# are reference types.",
    "options": [
      "False",
      "True"
    ],
    "correctAnswer": 0
  },
  {
    "id": "net-028",
    "category": ".NET",
    "difficulty": "medium",
    "type": "multiple-choice",
    "question": "What is the purpose of the IEnumerable interface?",
    "options": [
      "Enable iteration over collections",
      "Add sorting capabilities",
      "Make objects countable",
      "Define collection size"
    ],
    "correctAnswer": 0
  },
  {
    "id": "net-029",
    "category": ".NET",
    "difficulty": "medium",
    "type": "true-false",
    "question": "Exception handling in C# uses try-catch-finally blocks.",
    "options": [
      "True",
      "False"
    ],
    "correctAnswer": 0
  },
  {
    "id": "net-030",
    "category": ".NET",
    "difficulty": "medium",
    "type": "multiple-choice",
    "question": "What does CRUD represent in .NET applications?",
    "options": [
      "Core, Runtime, Utility, Data",
      "Cache, Read, Update, Delete",
      "Create, Read, Update, Delete",
      "Configure, Retrieve, Upgrade, Debug"
    ],
    "correctAnswer": 2
  },
  {
    "id": "net-031",
    "category": ".NET",
    "difficulty": "hard",
    "type": "multiple-choice",
    "question": "What is the difference between Task and Thread in .NET?",
    "options": [
      "Tasks run on threads; threads are OS-level",
      "Tasks can only run synchronously",
      "They are identical concepts",
      "Threads are always faster than tasks"
    ],
    "correctAnswer": 0
  },
  {
    "id": "net-032",
    "category": ".NET",
    "difficulty": "hard",
    "type": "true-false",
    "question": "Virtual methods in C# can be overridden by derived classes.",
    "options": [
      "False",
      "True"
    ],
    "correctAnswer": 1
  },
  {
    "id": "net-033",
    "category": ".NET",
    "difficulty": "hard",
    "type": "multiple-choice",
    "question": "What does the '?.' operator do in C#?",
    "options": [
      "Safe cast operator",
      "Conditional access operator",
      "Ternary operator",
      "Null coalescing operator"
    ],
    "correctAnswer": 1
  },
  {
    "id": "net-034",
    "category": ".NET",
    "difficulty": "hard",
    "type": "true-false",
    "question": "Reflection in C# allows inspecting and invoking members at runtime.",
    "options": [
      "True",
      "False"
    ],
    "correctAnswer": 0
  },
  {
    "id": "net-035",
    "category": ".NET",
    "difficulty": "hard",
    "type": "multiple-choice",
    "question": "What is the purpose of the lock statement in C#?",
    "options": [
      "Secure database connections",
      "Lock files from modification",
      "Encrypt data",
      "Prevent concurrent access to shared resources"
    ],
    "correctAnswer": 3
  },
  {
    "id": "net-036",
    "category": ".NET",
    "difficulty": "hard",
    "type": "true-false",
    "question": "IDisposable pattern is used for managing unmanaged resources.",
    "options": [
      "False",
      "True"
    ],
    "correctAnswer": 1
  },
  {
    "id": "net-037",
    "category": ".NET",
    "difficulty": "hard",
    "type": "multiple-choice",
    "question": "What does covariance enable in C# generics?",
    "options": [
      "Override generic constraints",
      "Mix different generic types",
      "Inherit from multiple generics",
      "Use derived types where base types are expected"
    ],
    "correctAnswer": 3
  },
  {
    "id": "net-038",
    "category": ".NET",
    "difficulty": "hard",
    "type": "true-false",
    "question": "Attributes in C# provide metadata but do not affect code execution.",
    "options": [
      "True",
      "False"
    ],
    "correctAnswer": 1
  },
  {
    "id": "net-039",
    "category": ".NET",
    "difficulty": "hard",
    "type": "multiple-choice",
    "question": "What is DbContext in Entity Framework?",
    "options": [
      "Cache manager",
      "Session to the database",
      "Query builder",
      "Data access layer"
    ],
    "correctAnswer": 1
  },
  {
    "id": "net-040",
    "category": ".NET",
    "difficulty": "hard",
    "type": "true-false",
    "question": "Yield keyword in C# enables lazy evaluation of collections.",
    "options": [
      "True",
      "False"
    ],
    "correctAnswer": 0
  },
  {
    "id": "net-041",
    "category": ".NET",
    "difficulty": "hard",
    "type": "multiple-choice",
    "question": "What is a race condition in multithreaded .NET applications?",
    "options": [
      "Unpredictable behavior when multiple threads access shared data",
      "Deadlock between threads",
      "Threads completing faster than expected",
      "Memory leak in thread pool"
    ],
    "correctAnswer": 0
  },
  {
    "id": "net-042",
    "category": ".NET",
    "difficulty": "hard",
    "type": "true-false",
    "question": "Partial classes in C# allow splitting a class across multiple files.",
    "options": [
      "True",
      "False"
    ],
    "correctAnswer": 0
  },
  {
    "id": "net-043",
    "category": ".NET",
    "difficulty": "hard",
    "type": "multiple-choice",
    "question": "What is an explicit interface implementation used for?",
    "options": [
      "Hide interface members from public API",
      "Force callers to use interface reference",
      "All of the above",
      "Implement multiple interfaces with conflicting members"
    ],
    "correctAnswer": 2
  },
  {
    "id": "net-044",
    "category": ".NET",
    "difficulty": "hard",
    "type": "true-false",
    "question": "The 'dynamic' type in C# is resolved at compile time.",
    "options": [
      "True",
      "False"
    ],
    "correctAnswer": 1
  },
  {
    "id": "net-045",
    "category": ".NET",
    "difficulty": "hard",
    "type": "multiple-choice",
    "question": "What does boxing and unboxing do in .NET?",
    "options": [
      "Convert value types to objects and vice versa",
      "Compress and decompress data",
      "Manage memory allocation",
      "Handle thread synchronization"
    ],
    "correctAnswer": 0
  },
  {
    "id": "net-046",
    "category": ".NET",
    "difficulty": "extra-hard",
    "type": "multiple-choice",
    "question": "What is the purpose of the 'volatile' keyword in C#?",
    "options": [
      "Make variables mutable",
      "Enable unsafe operations",
      "Ensure visibility of changes to shared variables in multithreading",
      "Prevent garbage collection"
    ],
    "correctAnswer": 2
  },
  {
    "id": "net-047",
    "category": ".NET",
    "difficulty": "extra-hard",
    "type": "true-false",
    "question": "Expression-bodied members in C# can only be used for properties.",
    "options": [
      "True",
      "False"
    ],
    "correctAnswer": 1
  },
  {
    "id": "net-048",
    "category": ".NET",
    "difficulty": "extra-hard",
    "type": "multiple-choice",
    "question": "What does constraint propagation in generics ensure?",
    "options": [
      "Type safety at compile time",
      "Backward compatibility",
      "Memory efficiency",
      "Runtime performance optimization"
    ],
    "correctAnswer": 0
  },
  {
    "id": "net-049",
    "category": ".NET",
    "difficulty": "extra-hard",
    "type": "true-false",
    "question": "Async void methods should be used for event handlers only.",
    "options": [
      "False",
      "True"
    ],
    "correctAnswer": 1
  },
  {
    "id": "net-050",
    "category": ".NET",
    "difficulty": "extra-hard",
    "type": "multiple-choice",
    "question": "What is the difference between lazy evaluation and eager evaluation in LINQ?",
    "options": [
      "Eager executes when query is defined; lazy executes when enumerated",
      "Lazy executes immediately; eager executes on demand",
      "Lazy is only for async operations",
      "They are the same concept"
    ],
    "correctAnswer": 0
  }
]